{
  "waitlist": {
    "title": "Zatiaľ obmedzujeme prístup",
    "subtitle": "Pripoj sa na čakaciu listinu pre prednostný prístup.",
    "emailPlaceholder": "Tvoja emailová adresa",
    "button": "Pridať sa na čakaciu listinu",
    "success": "Pridané!",
    "successMessage": "Dáme ti vedieť hneď, ako otvoríme miesto."
  },
  "login": {
    "title": "Vitaj späť",
    "subtitle": "Zadaj svoj e-mail pre prijatie odkazu na prihlásenie.",
    "emailPlaceholder": "tvoj@email.com",
    "button": "Poslať odkaz",
    "back": "Späť na úvod",
    "magicLinkSent": "Odkaz odoslaný!",
    "magicLinkMessage": "Skontroluj si e-mail s odkazom na prihlásenie."
  },
  "checkout": {
    "title": "Predplať si dennú mentálnu čistotu",
    "subtitle": "Okamžite si odomkni prémiové členstvo.",
    "productInfo": "Mindbanger Denník",
    "price": "€7,99",
    "perMonth": "/ mesačne",
    "features": [
      "Denný signál mysle",
      "Denné zameranie",
      "Denná afirmácia",
      "Audio reštart",
      "Prístup do archívu",
      "Bonusové reštarty"
    ],
    "formTitle": "Vytvoriť účet a zaplatiť",
    "firstName": "Krstné meno (Voliteľné)",
    "firstNamePlaceholder": "Napr. Ján",
    "email": "E-mailová adresa",
    "emailPlaceholder": "ty@priklad.sk",
    "submitBtn": "Pokračovať k platbe",
    "secureInfo": "Bezpečná platba cez Stripe. Zrušiť môžeš kedykoľvek."
  },
  "portal": {
    "title": "Tvoj denný reštart",
    "greeting": "Dobré ráno",
    "signalTab": "Dnešný signál",
    "archiveTab": "Archív",
    "settingsTab": "Nastavenia",
    "focusLabel": "Zameranie",
    "affirmationLabel": "Afirmácia",
    "playAudio": "Prehrať audio reštart",
    "audioUnsupported": "Tvoj prehliadač nepodporuje audio element.",
    "archiveTitle": "Archív signálov mysle",
    "noArchive": "Zatiaľ nemáš uložené žiadne minulé signály."
  },
  "settings": {
    "title": "Nastavenia",
    "account": "Účet",
    "email": "E-mail",
    "subscription": "Predplatné",
    "status": "Stav",
    "manageBilling": "Spravovať fakturáciu a predplatné",
    "language": "Jazyk",
    "logout": "Odhlásiť sa",
    "deleteTitle": "Zmazať účet",
    "deleteWarning": "Týmto natrvalo vymažeš svoj účet, históriu a predplatné.",
    "deleteBtn": "Zmazať môj účet",
    "confirmDelete": "Určite chceš zmazať svoj účet?"
  },
  "resets": {
    "backToProducts": "Späť na zoznam produktov",
    "audioNotAvailable": "Audio zatiaľ nie je k dispozícii."
  },
  "landing": {
    "waitlist": {
      "placeholder": "Tvoja e-mailová adresa",
      "button": "Pridať sa",
      "limited": "Zatiaľ prijímame iba obmedzený počet členov.",
      "success": "Ste na zozname!",
      "successSub": "Dáme vám vedieť hneď, ako spustíme ďalšiu vlnu."
    },
    "navbar": {
      "features": "Funkcie",
      "howItWorks": "Ako to funguje",
      "faq": "Časté otázky",
      "joinSub": "Pridať sa",
      "login": "Prihlásiť"
    },
    "hero": {
      "badge": "Mindbanger Daily",
      "titlePart1": "Nastavte svoju myseľ na ",
      "titleHighlight": "úspech",
      "titlePart2": " každý deň",
      "subtitle": "Denné signály mysle pre jasnosť, pokoj a sústredenie.<br className=\"hidden md:block\" />Vytvorené životným koučom a hypnoterapeutom.",
      "quote": "Spôsob, akým je vaša myseľ nastavená, začína formovať vašu realitu.",
      "widgetTitle": "Dnešný Signál",
      "widgetBadge": "Jasnosť",
      "widgetHeadline": "Zjednodušte si dnes jednu vec",
      "widgetQuote": "„Návratom k sebe sa vraciam k jasnosti.“",
      "widgetBtn": "Prehrať dnešné audio",
      "widgetFooter": "Nový signál každý deň. <br/> Silnejšie vnútorné smerovanie postupom času.",
      "subtitleDesc": "Denné signály pre jasnosť, pokoj a sústredenie.",
      "subtitleAuthor": "Vytvorené životným koučom a hypnoterapeutom."
    },
    "dailyRitual": {
      "title": "Každý deň v Mindbanger Daily:",
      "features": [
        {
          "title": "Téma dňa",
          "desc": "Určite si svoje denné smerovanie."
        },
        {
          "title": "Denný Mind Signál",
          "desc": "Vedená správa pre vaše nastavenie mysle."
        },
        {
          "title": "Dnešné zameranie",
          "desc": "Jeden praktický posun pre tento deň."
        },
        {
          "title": "Afirmácia",
          "desc": "Silné posilňujúce prehlásenie."
        },
        {
          "title": "Audio Reset",
          "desc": "Krátky upokojujúci hlasový reset."
        }
      ]
    },
    "howItWorks": {
      "title": "Ako to funguje",
      "steps": [
        {
          "title": "Pridať sa",
          "desc": "Začnite svoje členstvo za necelú minútu."
        },
        {
          "title": "Prijmite svoj denný signál",
          "desc": "Získajte čerstvú správu, zameranie, afirmáciu a audio reset."
        },
        {
          "title": "Zlepšujte svoju myseľ denne",
          "desc": "Postupom času si vytvoríte viac jasnosti, emocionálnej stability a smerovania."
        }
      ]
    },
    "interactivePreview": {
      "title": "Vyberte si slovo, ktoré vás ako prvé pritiahne",
      "options": [
        {
          "keyword": "Jasnosť",
          "desc": "Potrebujete menej hluku a jeden skutočný smer."
        },
        {
          "keyword": "Odvaha",
          "desc": "Malý úprimný krok dokáže zmeniť viac ako premýšľanie."
        },
        {
          "keyword": "Reset",
          "desc": "Dnes máte šancu uvoľniť včerajšiu záťaž."
        }
      ],
      "buttonActive": "Odomknúť celý denný signál pre {active}",
      "buttonInactive": "Odomknúť celý denný signál"
    },
    "benefits": {
      "title": "Mindbanger Daily je pre vás, ak chcete…",
      "items": [
        "Začať svoje rána s väčšou jasnosťou",
        "Znížiť vnútorný hluk a nadmerné premýšľanie",
        "Cítiť sa pokojnejšie a sústredenejšie",
        "Denne posilňovať svoje nastavenie mysle",
        "Znovu sa spojiť so sebou samým",
        "Prechádzať dňom s jasnejším smerovaním"
      ]
    },
    "vipZone": {
      "title": "Vo vnútri VIP Zóny",
      "cards": [
        {
          "title": "Dnes",
          "desc": "Váš denný signál, zameranie, afirmácia a audio."
        },
        {
          "title": "Archív",
          "desc": "Prístup k predchádzajúcim denným signálom kedykoľvek."
        },
        {
          "title": "Rýchle resety",
          "desc": "Pokojný reset, Reset sústredenia, Spánkový reset a ďalšie."
        },
        {
          "title": "Začnite tu",
          "desc": "Jednoduchý návod ako rituál používať pre najlepšie výsledky."
        }
      ]
    },
    "about": {
      "badge": "O Tvorcovi",
      "role": "Životný kouč, hypnoterapeut a sprievodca mentálnym výkonom.",
      "quote1": "Mindbanger Daily bol vytvorený, aby pomohol ľuďom formovať každý deň zvnútra von – prostredníctvom",
      "span1": "jasnosti",
      "quote2": ", ",
      "span2": "pokoja",
      "quote3": ", ",
      "span3": "sústredenia",
      "quote4": " a ",
      "span4": "zámerného mentálneho smerovania",
      "quote5": "."
    },
    "pricing": {
      "title1": "Jednoduchá denná podpora.",
      "title2": "Jeden mesačný plán.",
      "planName": "Mindbanger Daily",
      "price": "€7.90",
      "period": "/ mesiac",
      "subtitle": "Menej ako jedna káva týždenne.",
      "features": [
        "Denný mind signál",
        "Denné zameranie",
        "Denná afirmácia",
        "Audio reset",
        "Prístup do archívu",
        "Bonusové resety"
      ],
      "cancelText": "Zrušenie kedykoľvek. Žiadne otázky."
    },
    "faq": {
      "title": "Otázky",
      "faqs": [
        {
          "q": "Čo získam každý deň?",
          "a": "Dennú tému, krátky signál, zameranie, afirmáciu a audio reset."
        },
        {
          "q": "Je toto meditačná aplikácia?",
          "a": "Nie. Ide o denný rituál mysle určený pre jasnosť, pokoj a smerovanie."
        },
        {
          "q": "Môžem to kedykoľvek zrušiť?",
          "a": "Áno."
        },
        {
          "q": "Je obsah v slovenčine?",
          "a": "Áno. Aplikácia sa prispôsobí vášmu jazyku."
        },
        {
          "q": "Mám prístup k predchádzajúcim dňom?",
          "a": "Áno, prostredníctvom archívu."
        }
      ]
    },
    "finalCta": {
      "badge": "Začnite svoj denný reset",
      "title1": "Nastavte svoju myseľ.",
      "title2": "Formujte svoj deň.",
      "quote": "Spôsob, akým je vaša myseľ nastavená, začína formovať vašu realitu.",
      "footer": "Pridajte sa na čakaciu listinu Mindbanger Daily"
    },
    "footer": {
      "tagline": "Denné signály pre jasnosť, pokoj a sústredenie.",
      "login": "Prihlásiť",
      "join": "Pridať sa",
      "privacy": "Súkromie",
      "terms": "Podmienky"
    }
  }
}
